{
    "$schema": "http://schema.management.azure.com/schemas/2015-01-01/deploymentParameters.json#",
    "contentVersion": "1.0.0.0",
    "parameters": {
        "location": {
            "value": "West US"
        },
        "storageAccountType": {
            "value": "Standard_LRS"
        },
        "adminUsername": {
            "value": "admin123"
        },
        "adminPassword": {
            "value": "Hello!"
        },
        "publicIPAddressName": {
            "value": "samisrapublicipe2"
        },
        "storageAccountName": {
            "value": "samisraspstorage2"
        },
        "ipAddressPrefix": {
            "value": "192.168"
        }
    }
}
